README.md
setup.cfg
setup.py
litewax/__init__.py
litewax/abigen.py
litewax/client.py
litewax/contract.py
litewax/exceptions.py
litewax/multisigclient.py
litewax/paywith.py
litewax/types.py
litewax.egg-info/PKG-INFO
litewax.egg-info/SOURCES.txt
litewax.egg-info/dependency_links.txt
litewax.egg-info/not-zip-safe
litewax.egg-info/requires.txt
litewax.egg-info/top_level.txt