Metadata-Version: 2.1
Name: litewax
Version: 0.1.4
Summary: Simply python library for interact with (EOSIO) WAX blockchain
Home-page: https://github.com/makarworld/litewax.git
Author: abuztrade
Author-email: abuztrade.work@gmail.com
License: MIT License
Download-URL: https://github.com/makarworld/litewax/archive/refs/tags/v0.1.4.zip
Platform: UNKNOWN
Classifier: Development Status :: 4 - Beta
Classifier: Topic :: Communications :: Email
Classifier: Operating System :: OS Independent
Classifier: License :: OSI Approved :: MIT License
Classifier: Programming Language :: Python :: 3
Classifier: Programming Language :: Python :: 3.6
Classifier: Programming Language :: Python :: 3.7
Classifier: Programming Language :: Python :: 3.8
Classifier: Programming Language :: Python :: 3.9
Classifier: Programming Language :: Python :: 3.10
Classifier: Intended Audience :: Developers
Classifier: Intended Audience :: Customer Service
Classifier: Intended Audience :: Financial and Insurance Industry
Requires-Python: >=3.6.0
